{"name":"Find pets by multiple tags.","id":"everything-about-searching-pets.;find-pets-by-multiple-tags.","scenarioId":"classpath:features/pet/petSearchProcess:Find pets by multiple tags.","methodName":"Find pets by multiple tags.","testSteps":[{"number":1,"description":"Given exists some pets with this tags\r\n| brave |\r\n| friendly |\r\n| charming |","duration":121,"startTime":"2024-02-25T01:21:36.090694500-05:00[America/Bogota]","result":"SUCCESS","precondition":false,"level":0,"children":[{"number":2,"description":"Iván add new pet","duration":28,"startTime":"2024-02-25T01:21:36.112695-05:00[America/Bogota]","result":"SUCCESS","precondition":false,"level":1,"children":[{"number":3,"description":"Iván executes a POST on the resource /api/v3/pet","duration":21,"startTime":"2024-02-25T01:21:36.118696700-05:00[America/Bogota]","result":"SUCCESS","precondition":false,"level":2,"children":[{"number":4,"description":"POST http://localhost:8080/api/v3/pet","duration":0,"startTime":"2024-02-25T01:21:36.731775700-05:00[America/Bogota]","result":"SUCCESS","restQuery":{"method":"POST","path":"http://localhost:8080/api/v3/pet","content":"{\n    \"id\": \"1608240105\",\n    \"name\": \"Zeus\",\n    \"category\": {\n        \"id\": 1,\n        \"name\": \"Dogs\"\n    },\n    \"photoUrls\": [\n        \"/pet/photo/profile.jpg\"\n    ],\n    \"tags\": [\n        {\n            \"id\": 1,\n            \"name\": \"Dog\"\n        },\n        {\n            \"id\": 2,\n            \"name\": \"Friendly\"\n        },\n        {\n            \"id\": 36871,\n            \"name\": \"brave\"\n        }\n    ],\n    \"status\": \"available\"\n}","contentType":"application/json","requestHeaders":"Accept\u003d*/*\r\n\t\t\t\tContent-Type\u003dapplication/json","requestCookies":"","responseHeaders":"Date: Sun, 25 Feb 2024 06:21:36 GMT\r\nAccess-Control-Allow-Origin: *\r\nAccess-Control-Allow-Methods: GET, POST, DELETE, PUT\r\nAccess-Control-Allow-Headers: Content-Type, api_key, Authorization\r\nAccess-Control-Expose-Headers: Content-Disposition\r\nContent-Type: application/json\r\nContent-Length: 211\r\nServer: Jetty(9.4.9.v20180320)\r","responseCookies":"\r","responseBody":"{\n    \"id\": 1608240105,\n    \"category\": {\n        \"id\": 1,\n        \"name\": \"Dogs\"\n    },\n    \"name\": \"Zeus\",\n    \"photoUrls\": [\n        \"/pet/photo/profile.jpg\"\n    ],\n    \"tags\": [\n        {\n            \"id\": 1,\n            \"name\": \"Dog\"\n        },\n        {\n            \"id\": 2,\n            \"name\": \"Friendly\"\n        },\n        {\n            \"id\": 36871,\n            \"name\": \"brave\"\n        }\n    ],\n    \"status\": \"available\"\n}","statusCode":200},"precondition":false,"level":3}]}]},{"number":5,"description":"Iván add new pet","duration":23,"startTime":"2024-02-25T01:21:36.152221200-05:00[America/Bogota]","result":"SUCCESS","precondition":false,"level":1,"children":[{"number":6,"description":"Iván executes a POST on the resource /api/v3/pet","duration":16,"startTime":"2024-02-25T01:21:36.158221600-05:00[America/Bogota]","result":"SUCCESS","precondition":false,"level":2,"children":[{"number":7,"description":"POST http://localhost:8080/api/v3/pet","duration":0,"startTime":"2024-02-25T01:21:36.731775700-05:00[America/Bogota]","result":"SUCCESS","restQuery":{"method":"POST","path":"http://localhost:8080/api/v3/pet","content":"{\n    \"id\": \"1608240105\",\n    \"name\": \"Gracie\",\n    \"category\": {\n        \"id\": 1,\n        \"name\": \"Dogs\"\n    },\n    \"photoUrls\": [\n        \"/pet/photo/profile.jpg\"\n    ],\n    \"tags\": [\n        {\n            \"id\": 1,\n            \"name\": \"Dog\"\n        },\n        {\n            \"id\": 2,\n            \"name\": \"Friendly\"\n        },\n        {\n            \"id\": 36311,\n            \"name\": \"friendly\"\n        }\n    ],\n    \"status\": \"available\"\n}","contentType":"application/json","requestHeaders":"Accept\u003d*/*\r\n\t\t\t\tContent-Type\u003dapplication/json","requestCookies":"","responseHeaders":"Date: Sun, 25 Feb 2024 06:21:36 GMT\r\nAccess-Control-Allow-Origin: *\r\nAccess-Control-Allow-Methods: GET, POST, DELETE, PUT\r\nAccess-Control-Allow-Headers: Content-Type, api_key, Authorization\r\nAccess-Control-Expose-Headers: Content-Disposition\r\nContent-Type: application/json\r\nContent-Length: 216\r\nServer: Jetty(9.4.9.v20180320)\r","responseCookies":"\r","responseBody":"{\n    \"id\": 1608240105,\n    \"category\": {\n        \"id\": 1,\n        \"name\": \"Dogs\"\n    },\n    \"name\": \"Gracie\",\n    \"photoUrls\": [\n        \"/pet/photo/profile.jpg\"\n    ],\n    \"tags\": [\n        {\n            \"id\": 1,\n            \"name\": \"Dog\"\n        },\n        {\n            \"id\": 2,\n            \"name\": \"Friendly\"\n        },\n        {\n            \"id\": 36311,\n            \"name\": \"friendly\"\n        }\n    ],\n    \"status\": \"available\"\n}","statusCode":200},"precondition":false,"level":3}]}]},{"number":8,"description":"Iván add new pet","duration":24,"startTime":"2024-02-25T01:21:36.185844600-05:00[America/Bogota]","result":"SUCCESS","precondition":false,"level":1,"children":[{"number":9,"description":"Iván executes a POST on the resource /api/v3/pet","duration":17,"startTime":"2024-02-25T01:21:36.191847700-05:00[America/Bogota]","result":"SUCCESS","precondition":false,"level":2,"children":[{"number":10,"description":"POST http://localhost:8080/api/v3/pet","duration":0,"startTime":"2024-02-25T01:21:36.732778700-05:00[America/Bogota]","result":"SUCCESS","restQuery":{"method":"POST","path":"http://localhost:8080/api/v3/pet","content":"{\n    \"id\": \"1608240105\",\n    \"name\": \"Sandy\",\n    \"category\": {\n        \"id\": 1,\n        \"name\": \"Dogs\"\n    },\n    \"photoUrls\": [\n        \"/pet/photo/profile.jpg\"\n    ],\n    \"tags\": [\n        {\n            \"id\": 1,\n            \"name\": \"Dog\"\n        },\n        {\n            \"id\": 2,\n            \"name\": \"Friendly\"\n        },\n        {\n            \"id\": 23817,\n            \"name\": \"charming\"\n        }\n    ],\n    \"status\": \"available\"\n}","contentType":"application/json","requestHeaders":"Accept\u003d*/*\r\n\t\t\t\tContent-Type\u003dapplication/json","requestCookies":"","responseHeaders":"Date: Sun, 25 Feb 2024 06:21:36 GMT\r\nAccess-Control-Allow-Origin: *\r\nAccess-Control-Allow-Methods: GET, POST, DELETE, PUT\r\nAccess-Control-Allow-Headers: Content-Type, api_key, Authorization\r\nAccess-Control-Expose-Headers: Content-Disposition\r\nContent-Type: application/json\r\nContent-Length: 215\r\nServer: Jetty(9.4.9.v20180320)\r","responseCookies":"\r","responseBody":"{\n    \"id\": 1608240105,\n    \"category\": {\n        \"id\": 1,\n        \"name\": \"Dogs\"\n    },\n    \"name\": \"Sandy\",\n    \"photoUrls\": [\n        \"/pet/photo/profile.jpg\"\n    ],\n    \"tags\": [\n        {\n            \"id\": 1,\n            \"name\": \"Dog\"\n        },\n        {\n            \"id\": 2,\n            \"name\": \"Friendly\"\n        },\n        {\n            \"id\": 23817,\n            \"name\": \"charming\"\n        }\n    ],\n    \"status\": \"available\"\n}","statusCode":200},"precondition":false,"level":3}]}]}]},{"number":11,"description":"And we know that tag \"crazy\" doesn\u0027t exist","duration":216,"startTime":"2024-02-25T01:21:36.220328200-05:00[America/Bogota]","result":"SUCCESS","precondition":false,"level":0,"children":[{"number":12,"description":"Iván executes a GET on the resource /api/v3/pet/findByTags","duration":103,"startTime":"2024-02-25T01:21:36.237849300-05:00[America/Bogota]","result":"SUCCESS","precondition":false,"level":1,"children":[{"number":13,"description":"GET http://localhost:8080/api/v3/pet/findByTags?tags\u003dcrazy","duration":0,"startTime":"2024-02-25T01:21:36.732778700-05:00[America/Bogota]","result":"SUCCESS","restQuery":{"method":"GET","path":"http://localhost:8080/api/v3/pet/findByTags?tags\u003dcrazy","content":"","contentType":"application/json","requestHeaders":"Accept\u003d*/*\r\n\t\t\t\tContent-Type\u003dapplication/json","requestCookies":"","responseHeaders":"Date: Sun, 25 Feb 2024 06:21:36 GMT\r\nAccess-Control-Allow-Origin: *\r\nAccess-Control-Allow-Methods: GET, POST, DELETE, PUT\r\nAccess-Control-Allow-Headers: Content-Type, api_key, Authorization\r\nAccess-Control-Expose-Headers: Content-Disposition\r\nContent-Type: application/json\r\nContent-Length: 2\r\nServer: Jetty(9.4.9.v20180320)\r","responseCookies":"\r","responseBody":"[\n    \n]","statusCode":200},"precondition":false,"level":2}]},{"number":14,"description":"Iván should see  that is false","duration":15,"startTime":"2024-02-25T01:21:36.420216800-05:00[America/Bogota]","result":"SUCCESS","precondition":false,"level":1}]},{"number":15,"description":"When the employee search by all mentioned tags before","duration":50,"startTime":"2024-02-25T01:21:36.436834900-05:00[America/Bogota]","result":"SUCCESS","precondition":false,"level":0,"children":[{"number":16,"description":"Iván executes a GET on the resource /api/v3/pet/findByTags","duration":43,"startTime":"2024-02-25T01:21:36.441835300-05:00[America/Bogota]","result":"SUCCESS","precondition":false,"level":1,"children":[{"number":17,"description":"GET http://localhost:8080/api/v3/pet/findByTags?tags\u003dbrave\u0026tags\u003dfriendly\u0026tags\u003dcharming\u0026tags\u003dcrazy","duration":0,"startTime":"2024-02-25T01:21:36.733777200-05:00[America/Bogota]","result":"SUCCESS","restQuery":{"method":"GET","path":"http://localhost:8080/api/v3/pet/findByTags?tags\u003dbrave\u0026tags\u003dfriendly\u0026tags\u003dcharming\u0026tags\u003dcrazy","content":"","contentType":"application/json","requestHeaders":"Accept\u003d*/*\r\n\t\t\t\tContent-Type\u003dapplication/json","requestCookies":"","responseHeaders":"Date: Sun, 25 Feb 2024 06:21:36 GMT\r\nAccess-Control-Allow-Origin: *\r\nAccess-Control-Allow-Methods: GET, POST, DELETE, PUT\r\nAccess-Control-Allow-Headers: Content-Type, api_key, Authorization\r\nAccess-Control-Expose-Headers: Content-Disposition\r\nContent-Type: application/json\r\nContent-Length: 217\r\nServer: Jetty(9.4.9.v20180320)\r","responseCookies":"\r","responseBody":"[\n    {\n        \"id\": 1608240105,\n        \"category\": {\n            \"id\": 1,\n            \"name\": \"Dogs\"\n        },\n        \"name\": \"Sandy\",\n        \"photoUrls\": [\n            \"/pet/photo/profile.jpg\"\n        ],\n        \"tags\": [\n            {\n                \"id\": 1,\n                \"name\": \"Dog\"\n            },\n            {\n                \"id\": 2,\n                \"name\": \"Friendly\"\n            },\n            {\n                \"id\": 23817,\n                \"name\": \"charming\"\n            }\n        ],\n        \"status\": \"available\"\n    }\n]","statusCode":200},"precondition":false,"level":2}]}]},{"number":18,"description":"Then he will see a list of pets related only with existing tags","duration":0,"startTime":"2024-02-25T01:21:36.487075300-05:00[America/Bogota]","result":"SUCCESS","precondition":false,"level":0}],"userStory":{"id":"classpath:features/pet/petSearchProcess","storyName":"Everything about searching Pets.","displayName":"Everything about searching Pets.","path":"pet/petSearchProcess","pathElements":[{"name":"pet","description":""},{"name":"petSearchProcess","description":""}],"narrative":"  As a pet store employee\n  I need to search some enrolled pets\n  to verify some information about customers.","type":"feature"},"title":"Find pets by multiple tags.","description":"","startTime":"2024-02-25T01:21:36.057613400-05:00[America/Bogota]","duration":674,"projectKey":"","isManualTestingUpToDate":false,"manual":false,"testSource":"Cucumber","actors":[{"name":"Iván"}],"result":"SUCCESS"}